MANIFEST.in
Makefile
README.rst
pycd10api.ini
requirements-test.txt
requirements.txt
setup.py
data/get_icd10.sh
pycd10api/__init__.py
pycd10api/views.py
pycd10api.egg-info/PKG-INFO
pycd10api.egg-info/SOURCES.txt
pycd10api.egg-info/dependency_links.txt
pycd10api.egg-info/entry_points.txt
pycd10api.egg-info/not-zip-safe
pycd10api.egg-info/requires.txt
pycd10api.egg-info/top_level.txt
pycd10api/icd/__init__.py
pycd10api/icd/cm.py