Metadata-Version: 1.1
Name: pycd10api
Version: 0.2.2
Summary: pycd10api
Home-page: https://github.com/westurner/pycd10api
Author: Wes Turner
Author-email: wes@wrd.nu
License: UNKNOWN
Keywords: ICD10 REST API pyramid cornice
Platform: UNKNOWN
Classifier: Programming Language :: Python
Classifier: Framework :: Pyramid
Classifier: Topic :: Internet :: WWW/HTTP
Classifier: Topic :: Internet :: WWW/HTTP :: WSGI :: Application
Classifier: Intended Audience :: Healthcare Industry
